mseep_mxcp-0.6.2.dist-info/licenses/LICENSE
mxcp/__main__.py
mxcp/py.typed
mxcp/plugins/__init__.py
mxcp/plugins/_types.py
mxcp/plugins/base.py
mxcp/runtime/__init__.py
mxcp/sdk/__init__.py
mxcp/sdk/audit/__init__.py
mxcp/sdk/audit/_types.py
mxcp/sdk/audit/logger.py
mxcp/sdk/audit/query.py
mxcp/sdk/audit/redaction.py
mxcp/sdk/audit/writer.py
mxcp/sdk/audit/backends/__init__.py
mxcp/sdk/audit/backends/jsonl.py
mxcp/sdk/audit/backends/noop.py
mxcp/sdk/auth/__init__.py
mxcp/sdk/auth/_types.py
mxcp/sdk/auth/base.py
mxcp/sdk/auth/context.py
mxcp/sdk/auth/middleware.py
mxcp/sdk/auth/persistence.py
mxcp/sdk/auth/url_utils.py
mxcp/sdk/auth/providers/__init__.py
mxcp/sdk/auth/providers/atlassian.py
mxcp/sdk/auth/providers/github.py
mxcp/sdk/auth/providers/google.py
mxcp/sdk/auth/providers/keycloak.py
mxcp/sdk/auth/providers/salesforce.py
mxcp/sdk/core/__init__.py
mxcp/sdk/core/version.py
mxcp/sdk/core/analytics/__init__.py
mxcp/sdk/core/config/__init__.py
mxcp/sdk/core/config/_types.py
mxcp/sdk/core/config/loader.py
mxcp/sdk/core/config/plugins.py
mxcp/sdk/core/config/processor.py
mxcp/sdk/core/config/resolvers/__init__.py
mxcp/sdk/core/config/resolvers/env.py
mxcp/sdk/core/config/resolvers/file.py
mxcp/sdk/core/config/resolvers/onepassword.py
mxcp/sdk/core/config/resolvers/vault.py
mxcp/sdk/core/config/schemas/resolver-config-schema.json
mxcp/sdk/evals/__init__.py
mxcp/sdk/evals/_types.py
mxcp/sdk/evals/executor.py
mxcp/sdk/executor/__init__.py
mxcp/sdk/executor/context.py
mxcp/sdk/executor/interfaces.py
mxcp/sdk/executor/plugins/__init__.py
mxcp/sdk/executor/plugins/duckdb.py
mxcp/sdk/executor/plugins/python.py
mxcp/sdk/executor/plugins/duckdb_plugin/__init__.py
mxcp/sdk/executor/plugins/duckdb_plugin/_types.py
mxcp/sdk/executor/plugins/duckdb_plugin/extension_loader.py
mxcp/sdk/executor/plugins/duckdb_plugin/plugin_loader.py
mxcp/sdk/executor/plugins/duckdb_plugin/secret_injection.py
mxcp/sdk/executor/plugins/duckdb_plugin/session.py
mxcp/sdk/executor/plugins/python_plugin/__init__.py
mseep_mxcp-0.6.2.dist-info/METADATA
mseep_mxcp-0.6.2.dist-info/WHEEL
mseep_mxcp-0.6.2.dist-info/entry_points.txt
mseep_mxcp-0.6.2.dist-info/top_level.txt
mseep_mxcp-0.6.2.dist-info/RECORD
